qplay_cli/__init__.py
qplay_cli/main.py
qplay_cli/api_clients/__init__.py
qplay_cli/api_clients/instance_api.py
qplay_cli/api_clients/market_api.py
qplay_cli/api_clients/qplay.py
qplay_cli/api_clients/strategy_service.py
qplay_cli/api_clients/user_api.py
qplay_cli/api_clients/volume_api.py
qplay_cli/backtest/__init__.py
qplay_cli/backtest/backtesting.py
qplay_cli/backtest/commands.py
qplay_cli/broker/__init__.py
qplay_cli/broker/commands.py
qplay_cli/broker/zerodha/__init__.py
qplay_cli/broker/zerodha/kite_utils.py
qplay_cli/broker/zerodha/z_broker.py
qplay_cli/config/__init__.py
qplay_cli/config/qplay_config.py
qplay_cli/dataset/__init__.py
qplay_cli/dataset/commands.py
qplay_cli/dataset/volume.py
qplay_cli/executor/__init__.py
qplay_cli/executor/strategy_executor.py
qplay_cli/machine/__init__.py
qplay_cli/machine/commands.py
qplay_cli/market/__init__.py
qplay_cli/market/commands.py
qplay_cli/strategy/__init__.py
qplay_cli/strategy/commands.py
qplay_cli/user/__init__.py
qplay_cli/user/commands.py
qplay_cli/utils/__init__.py
qplay_cli/utils/file_utils.py
qplay_cli/utils/selenium_utils.py
qplay_cli-1.1.12.dist-info/METADATA
qplay_cli-1.1.12.dist-info/WHEEL
qplay_cli-1.1.12.dist-info/entry_points.txt
qplay_cli-1.1.12.dist-info/top_level.txt
qplay_cli-1.1.12.dist-info/RECORD
