Metadata-Version: 2.1
Name: qplay-cli
Version: 1.1.12
Requires-Dist: Click
Requires-Dist: requests
Requires-Dist: retrying
Requires-Dist: pyotp
Requires-Dist: ec2-metadata
Requires-Dist: selenium (>=4.5.0)
Requires-Dist: gdown
Requires-Dist: kiteconnect
Requires-Dist: tabulate
Requires-Dist: quantplay (>=1.0.90)
